README.md
setup.py
test/test_get_credentials_from_file.py
test/test_load_from_vcap_services.py
test/test_parse_credentials.py
vcap_services/__init__.py
vcap_services/index.py
vcap_services.egg-info/PKG-INFO
vcap_services.egg-info/SOURCES.txt
vcap_services.egg-info/dependency_links.txt
vcap_services.egg-info/top_level.txt
vcap_services.egg-info/zip-safe