Metadata-Version: 1.0
Name: vcap-services
Version: 1.0.0
Summary: Client library to parse and return service credentials from environment variables that IBM Cloud provides.
Home-page: https://github.com/mamoonraja/vcap-services-python
Author: Mamoon Raja
Author-email: mamoon.raja@ibm.com
License: Apache 2.0
Platform: UNKNOWN
